storas/__init__.py
storas/commands.py
storas/main.py
storas/manifest.py
storas/py.typed
storas-0.7.dist-info/METADATA
storas-0.7.dist-info/WHEEL
storas-0.7.dist-info/top_level.txt
storas-0.7.dist-info/RECORD
