Metadata-Version: 2.1
Name: storas
Version: 0.7
Summary: A module for working with Android repo (repotool, git-repo) manifest files
Home-page: https://github.com/EliRibble/storas
Author: Eli Ribble
Author-email: eliribble@google.com
License: UNKNOWN
Platform: UNKNOWN
Requires-Python: >=3.6
Provides-Extra: develop
Requires-Dist: mypy ; extra == 'develop'
Requires-Dist: nose2 ; extra == 'develop'
Requires-Dist: pre-commit ; extra == 'develop'
Requires-Dist: pylint ; extra == 'develop'
Requires-Dist: twine ; extra == 'develop'
Requires-Dist: wheel ; extra == 'develop'
